setup.py
horntell/__init__.py
horntell/app.py
horntell/campaign.py
horntell/card.py
horntell/errors.py
horntell/event.py
horntell/horn.py
horntell/profile.py
horntell.egg-info/PKG-INFO
horntell.egg-info/SOURCES.txt
horntell.egg-info/dependency_links.txt
horntell.egg-info/requires.txt
horntell.egg-info/top_level.txt
horntell/http/__init__.py
horntell/http/client.py
horntell/http/request.py
horntell/http/response.py