Metadata-Version: 1.0
Name: horntell
Version: 0.3.0
Summary: Horntell SDK for Python
Home-page: https://github.com/horntell/python-sdk
Author: Mohit Mamoria
Author-email: mohit@horntell.com
License: UNKNOWN
Platform: UNKNOWN
